comopy/__init__.py
comopy/bits.py
comopy/config/__init__.py
comopy/config/context.py
comopy/config/ir_config.py
comopy/config/sim_config.py
comopy/config/trans_config.py
comopy/datatypes/__init__.py
comopy/datatypes/bit_pat.py
comopy/datatypes/bits.py
comopy/datatypes/bits_data.py
comopy/datatypes/bits_n.py
comopy/datatypes/param_const.py
comopy/datatypes/tests/__init__.py
comopy/datatypes/tests/bit_pat_test.py
comopy/datatypes/tests/bits_data_test.py
comopy/datatypes/tests/bits_match_test.py
comopy/datatypes/tests/bits_n_test.py
comopy/datatypes/tests/bits_test.py
comopy/datatypes/tests/param_const_test.py
comopy/hdl/__init__.py
comopy/hdl/assemble_hdl.py
comopy/hdl/circuit_node.py
comopy/hdl/circuit_object.py
comopy/hdl/connectable.py
comopy/hdl/hdl_stage.py
comopy/hdl/io_struct.py
comopy/hdl/module.py
comopy/hdl/package.py
comopy/hdl/parameter.py
comopy/hdl/raw_module.py
comopy/hdl/signal.py
comopy/hdl/signal_array.py
comopy/hdl/signal_bundle.py
comopy/hdl/signal_slice.py
comopy/hdl/tagged_class.py
comopy/hdl/tests/__init__.py
comopy/hdl/tests/assemble_hdl_test.py
comopy/hdl/tests/circuit_node_test.py
comopy/hdl/tests/circuit_object_test.py
comopy/hdl/tests/connectable_test.py
comopy/hdl/tests/errors_test.py
comopy/hdl/tests/hdl_stage_test.py
comopy/hdl/tests/io_struct_test.py
comopy/hdl/tests/module_test.py
comopy/hdl/tests/parameter_test.py
comopy/hdl/tests/raw_module_test.py
comopy/hdl/tests/signal_array_test.py
comopy/hdl/tests/signal_bundle_test.py
comopy/hdl/tests/signal_slice_test.py
comopy/hdl/tests/signal_test.py
comopy/hdl/tests/tagged_class_test.py
comopy/ir/__init__.py
comopy/ir/aux_ir.py
comopy/ir/behavior_pass.py
comopy/ir/circt_ir.py
comopy/ir/function_parser.py
comopy/ir/generate_ir.py
comopy/ir/ir_stage.py
comopy/ir/object_parser.py
comopy/ir/parser_defs.py
comopy/ir/structure_pass.py
comopy/ir/tests/__init__.py
comopy/ir/tests/behavior_pass_test.py
comopy/ir/tests/errors_test.py
comopy/ir/tests/function_parser_test.py
comopy-0.6.0.dist-info/licenses/LICENSE
comopy-0.6.0.dist-info/METADATA
comopy-0.6.0.dist-info/WHEEL
comopy-0.6.0.dist-info/top_level.txt
comopy-0.6.0.dist-info/RECORD
