Metadata-Version: 2.4
Name: comopy
Version: 0.6.0
Summary: Co-modeling tools for hardware generation with Python
Author: Microprocessor R&D Center (MPRC), Peking University
Maintainer: Chun Yang
License: MIT
Project-URL: Homepage, https://github.com/mprcpku/comopy
Project-URL: Repository, https://github.com/mprcpku/comopy
Project-URL: Issues, https://github.com/mprcpku/comopy/issues
Keywords: hardware,hdl,simulation,rtl,verilog
Classifier: Development Status :: 3 - Alpha
Classifier: Intended Audience :: Developers
Classifier: Intended Audience :: Science/Research
Classifier: License :: OSI Approved :: MIT License
Classifier: Operating System :: POSIX :: Linux
Classifier: Programming Language :: Python :: 3
Classifier: Programming Language :: Python :: 3 :: Only
Classifier: Programming Language :: Python :: 3.13
Classifier: Topic :: Scientific/Engineering :: Electronic Design Automation (EDA)
Classifier: Topic :: Software Development :: Code Generators
Classifier: Topic :: Software Development :: Testing
Requires-Python: >=3.13
License-File: LICENSE
Requires-Dist: circt~=1.125.0
Requires-Dist: jinja2>=3.1
Requires-Dist: pybind11>=2.13.0
Requires-Dist: setuptools>=59.0
Provides-Extra: dev
Requires-Dist: pytest>=8.4; extra == "dev"
Requires-Dist: pytest-cov>=6.2; extra == "dev"
Requires-Dist: types-setuptools>=80.9; extra == "dev"
Dynamic: license-file
